{
	"version": "2.0",
	"name": "superior3",
	"description": "",
	"points": 523577,
	"projection": "",
	"hierarchy": {
		"firstChunkSize": 4246, 
		"stepSize": 4, 
		"depth": 4
	},
	"offset": [-2.7784004211425781, -3.0634663105010986, -2.5129999999999999],
	"scale": [0.001, 0.001, 0.001],
	"spacing": 0.085015624999999997,
	"boundingBox": {
		"min": [-2.7784004211425781, -3.0634663105010986, -2.5129999999999999], 
		"max": [8.1035995788574215, 7.818533689498901, 8.3689999999999998]
	},
	"encoding": "DEFAULT",
	"attributes": [
		{
			"name": "position",
			"description": "",
			"size": 12,
			"numElements": 3,
			"elementSize": 4,
			"type": "int32",
			"min": [-2.7784004211425781, -3.0634663105010986, -2.5129999999999999],
			"max": [8.1035995788574215, 6.438533689498902, 3.573],
			"scale": [1, 1, 1],
			"offset": [0, 0, 0]
		},{
			"name": "intensity",
			"description": "",
			"size": 2,
			"numElements": 1,
			"elementSize": 2,
			"type": "uint16",
			"min": [0],
			"max": [0],
			"scale": [1],
			"offset": [0]
		},{
			"name": "return number",
			"description": "",
			"size": 1,
			"numElements": 1,
			"elementSize": 1,
			"type": "uint8",
			"min": [0],
			"max": [0],
			"scale": [1],
			"offset": [0]
		},{
			"name": "number of returns",
			"description": "",
			"size": 1,
			"numElements": 1,
			"elementSize": 1,
			"type": "uint8",
			"min": [0],
			"max": [0],
			"scale": [1],
			"offset": [0]
		},{
			"name": "classification",
			"description": "",
			"size": 1,
			"numElements": 1,
			"elementSize": 1,
			"type": "uint8",
			"histogram": [523577, 0, 0, 0, 0, 0, 0, 0, 0, 0, 0, 0, 0, 0, 0, 0, 0, 0, 0, 0, 0, 0, 0, 0, 0, 0, 0, 0, 0, 0, 0, 0, 0, 0, 0, 0, 0, 0, 0, 0, 0, 0, 0, 0, 0, 0, 0, 0, 0, 0, 0, 0, 0, 0, 0, 0, 0, 0, 0, 0, 0, 0, 0, 0, 0, 0, 0, 0, 0, 0, 0, 0, 0, 0, 0, 0, 0, 0, 0, 0, 0, 0, 0, 0, 0, 0, 0, 0, 0, 0, 0, 0, 0, 0, 0, 0, 0, 0, 0, 0, 0, 0, 0, 0, 0, 0, 0, 0, 0, 0, 0, 0, 0, 0, 0, 0, 0, 0, 0, 0, 0, 0, 0, 0, 0, 0, 0, 0, 0, 0, 0, 0, 0, 0, 0, 0, 0, 0, 0, 0, 0, 0, 0, 0, 0, 0, 0, 0, 0, 0, 0, 0, 0, 0, 0, 0, 0, 0, 0, 0, 0, 0, 0, 0, 0, 0, 0, 0, 0, 0, 0, 0, 0, 0, 0, 0, 0, 0, 0, 0, 0, 0, 0, 0, 0, 0, 0, 0, 0, 0, 0, 0, 0, 0, 0, 0, 0, 0, 0, 0, 0, 0, 0, 0, 0, 0, 0, 0, 0, 0, 0, 0, 0, 0, 0, 0, 0, 0, 0, 0, 0, 0, 0, 0, 0, 0, 0, 0, 0, 0, 0, 0, 0, 0, 0, 0, 0, 0, 0, 0, 0, 0, 0, 0, 0, 0, 0, 0, 0, 0, 0, 0, 0, 0, 0, 0], 
			"min": [0],
			"max": [0],
			"scale": [1],
			"offset": [0]
		},{
			"name": "scan angle rank",
			"description": "",
			"size": 1,
			"numElements": 1,
			"elementSize": 1,
			"type": "uint8",
			"min": [0],
			"max": [0],
			"scale": [1],
			"offset": [0]
		},{
			"name": "user data",
			"description": "",
			"size": 1,
			"numElements": 1,
			"elementSize": 1,
			"type": "uint8",
			"min": [0],
			"max": [0],
			"scale": [1],
			"offset": [0]
		},{
			"name": "point source id",
			"description": "",
			"size": 2,
			"numElements": 1,
			"elementSize": 2,
			"type": "uint16",
			"min": [0],
			"max": [0],
			"scale": [1],
			"offset": [0]
		},{
			"name": "rgb",
			"description": "",
			"size": 6,
			"numElements": 3,
			"elementSize": 2,
			"type": "uint16",
			"min": [0, 0, 0],
			"max": [65280, 65280, 65280],
			"scale": [1, 1, 1],
			"offset": [0, 0, 0]
		},{
			"name": "Scalar field",
			"description": "",
			"size": 4,
			"numElements": 1,
			"elementSize": 4,
			"type": "float",
			"min": [0],
			"max": [65534],
			"scale": [1],
			"offset": [0]
		},{
			"name": "Scalar field #2",
			"description": "",
			"size": 4,
			"numElements": 1,
			"elementSize": 4,
			"type": "float",
			"min": [1],
			"max": [1],
			"scale": [1],
			"offset": [0]
		},{
			"name": "Scalar field #3",
			"description": "",
			"size": 4,
			"numElements": 1,
			"elementSize": 4,
			"type": "float",
			"min": [1],
			"max": [1],
			"scale": [1],
			"offset": [0]
		}
	]
}
